spsscamera/__init__.py
spsscamera/camera.py
spsscamera/image_processing.py
tests/__init__.py
tests/test_camera.py
spsscamera-0.1.0.dist-info/LICENSE
spsscamera-0.1.0.dist-info/METADATA
spsscamera-0.1.0.dist-info/WHEEL
spsscamera-0.1.0.dist-info/top_level.txt
spsscamera-0.1.0.dist-info/RECORD
