Metadata-Version: 2.2
Name: spsscamera
Version: 0.1.0
Summary: A library to access the device's camera and preprocess images for decoding.
Home-page: https://github.com/yourusername/spsscamera
Author: Sumedh Patil
Author-email: admin@aipresso.uk
Classifier: Programming Language :: Python :: 3
Classifier: License :: OSI Approved :: MIT License
Classifier: Operating System :: OS Independent
Requires-Python: >=3.7
License-File: LICENSE
Dynamic: author
Dynamic: author-email
Dynamic: classifier
Dynamic: description
Dynamic: description-content-type
Dynamic: home-page
Dynamic: requires-python
Dynamic: summary
